ygka/__init__.py
ygka/__main__.py
ygka/cli/__init__.py
ygka/cli/cli_app.py
ygka/cli/config_ygka.py
ygka/cli/retrieve_stdin.py
ygka/cli/ygka.py
ygka/exceptions/__init__.py
ygka/exceptions/unauthorized_access_error.py
ygka/models/__init__.py
ygka/models/language_model.py
ygka/models/revchatgpt_chatbot_config_model.py
ygka/models/str_enum.py
ygka/models/ygka_config_model.py
ygka/query_clients/__init__.py
ygka/query_clients/official_chatgpt_client.py
ygka/query_clients/query_client.py
ygka/query_clients/query_client_factory.py
ygka/query_clients/reverse_engineered_chatgpt_client.py
ygka/tests/__init__.py
ygka/tests/test_sample.py
ygka/utils/__init__.py
ygka/utils/test/test_ygka_config_manager.py
ygka/utils/ygka_config_manager.py
ygka-2023.4.16.post1.dist-info/LICENSE
ygka-2023.4.16.post1.dist-info/METADATA
ygka-2023.4.16.post1.dist-info/WHEEL
ygka-2023.4.16.post1.dist-info/entry_points.txt
ygka-2023.4.16.post1.dist-info/RECORD
